mcot/__init__.py
mcot/surface/README.rst
mcot/surface/VERSION
mcot/surface/__init__.py
mcot/surface/_write_gifti.py
mcot/surface/all.py
mcot/surface/cortex.py
mcot/surface/cortical_mesh.py
mcot/surface/grid.py
mcot/surface/mesh.py
mcot/surface/test_data.py
mcot/surface/track.py
mcot/surface/utils.py
mcot/surface/_scripts/__init__.py
mcot/surface/_scripts/ptx/__init__.py
mcot/surface/_scripts/ptx/select_vertex.py
mcot/surface/_scripts/surface/__init__.py
mcot/surface/_scripts/surface/__main__.py
mcot/surface/_scripts/surface/from_mask.py
mcot/surface/_scripts/surface/from_ridge.py
mcot/surface/_scripts/surface/roi_dist_gifti.py
mcot/surface/_scripts/surface/smooth.py
mcot/surface/_scripts/surface/watershed.py
mcot.surface-0.2.0.dist-info/METADATA
mcot.surface-0.2.0.dist-info/WHEEL
mcot.surface-0.2.0.dist-info/namespace_packages.txt
mcot.surface-0.2.0.dist-info/top_level.txt
mcot.surface-0.2.0.dist-info/RECORD
